MANIFEST.in
setup.py
django_jsonmodel.egg-info/PKG-INFO
django_jsonmodel.egg-info/SOURCES.txt
django_jsonmodel.egg-info/dependency_links.txt
django_jsonmodel.egg-info/requires.txt
django_jsonmodel.egg-info/top_level.txt
djangojsonmodel/__init__.py
djangojsonmodel/convert.py
djangojsonmodel/db.py
djangojsonmodel/util.py
djangojsonmodel/contrib/__init__.py
djangojsonmodel/contrib/db/__init__.py
djangojsonmodel/contrib/db/rel.py
djangojsonmodel/contrib/file/save.py
djangojsonmodel/contrib/html/__init__.py
djangojsonmodel/contrib/html/producer.py
djangojsonmodel/contrib/human/__init__.py
djangojsonmodel/contrib/human/mappings.py
djangojsonmodel/contrib/human/urls.py
djangojsonmodel/contrib/representation/__init__.py
djangojsonmodel/contrib/representation/json.py
test/test_conversion.py
test/test_human.py
test/test_implied.py
test/test_representation.py