Metadata-Version: 1.0
Name: django-jsonmodel
Version: 0.0.10
Summary: Convert Django Models to a JSON representation
Home-page: http://github.com/futurice-oss/django-jsonmodel
Author: Jussi Vaihia
Author-email: jussi.vaihia@futurice.com
License: MIT
Keywords: django json models js javascript
Platform: UNKNOWN
